addno/__init__.py
addno-0.1.0.dist-info/licenses/LICENSE
addno-0.1.0.dist-info/METADATA
addno-0.1.0.dist-info/WHEEL
addno-0.1.0.dist-info/top_level.txt
addno-0.1.0.dist-info/RECORD
